jsontableschema_sql/VERSION
jsontableschema_sql/__init__.py
jsontableschema_sql/mappers.py
jsontableschema_sql/storage.py
jsontableschema_sql/writer.py
jsontableschema_sql-0.8.0.dist-info/DESCRIPTION.rst
jsontableschema_sql-0.8.0.dist-info/METADATA
jsontableschema_sql-0.8.0.dist-info/RECORD
jsontableschema_sql-0.8.0.dist-info/WHEEL
jsontableschema_sql-0.8.0.dist-info/metadata.json
jsontableschema_sql-0.8.0.dist-info/top_level.txt
