Metadata-Version: 2.0
Name: jsontableschema-sql
Version: 0.8.0
Summary: Generate SQL tables, load and extract data, based on JSON Table Schema descriptors.
Home-page: https://github.com/frictionlessdata/jsontableschema-sql-py
Author: Open Knowledge Foundation
Author-email: info@okfn.org
License: MIT
Keywords: frictionless data
Platform: UNKNOWN
Classifier: Development Status :: 4 - Beta
Classifier: Environment :: Web Environment
Classifier: Intended Audience :: Developers
Classifier: License :: OSI Approved :: MIT License
Classifier: Operating System :: OS Independent
Classifier: Programming Language :: Python :: 2
Classifier: Programming Language :: Python :: 2.7
Classifier: Programming Language :: Python :: 3
Classifier: Programming Language :: Python :: 3.3
Classifier: Programming Language :: Python :: 3.4
Classifier: Programming Language :: Python :: 3.5
Classifier: Topic :: Internet :: WWW/HTTP :: Dynamic Content
Classifier: Topic :: Software Development :: Libraries :: Python Modules
Requires-Dist: jsontableschema (>=0.7,<1.0)
Requires-Dist: pybloom-live (<3.0,>=2.2)
Requires-Dist: six (>=1.9,<2.0)
Requires-Dist: sqlalchemy (>=1.0,<2.0)
Requires-Dist: tabulator (>=1.0.0a5,<2.0)
Provides-Extra: develop
Requires-Dist: psycopg2; extra == 'develop'
Requires-Dist: pylama; extra == 'develop'
Requires-Dist: python-dotenv; extra == 'develop'
Requires-Dist: tox; extra == 'develop'
